{
  "rumble": {
    "subtitle": "sounds.luckysspelunkerscharm.rumble",
    "sounds": [
      "luckysspelunkerscharm:ambient/cave/rumble_0"
      ]
  },
  "tremor": {
    "subtitle": "sounds.luckysspelunkerscharm.tremor",
    "sounds": [
      {
        "name": "luckysspelunkerscharm:ambient/cave/tremor_0",
        "stream": false,
        "attenuation_distance": 64
      }
    ]
  },
  "geyser_charge": {
    "subtitle": "sounds.luckysspelunkerscharm.geyser_charge",
    "sounds": [
      "luckysspelunkerscharm:block/geyser/charge_0",
      "luckysspelunkerscharm:block/geyser/charge_1"
    ]
  },
  "geyser_erupt_water": {
    "subtitle": "sounds.luckysspelunkerscharm.geyser_erupt_water",
    "sounds": [
      "luckysspelunkerscharm:block/geyser/erupt_water_0",
      "luckysspelunkerscharm:block/geyser/erupt_water_1",
      "luckysspelunkerscharm:block/geyser/erupt_water_2",
      "luckysspelunkerscharm:block/geyser/erupt_water_3",
      "luckysspelunkerscharm:block/geyser/erupt_water_4"
    ]
  }
}